chinese2digits/__init__.py
chinese2digits/chinese2digits.py
chinese2digits/test.py
chinese2digits-6.0.1.dist-info/METADATA
chinese2digits-6.0.1.dist-info/WHEEL
chinese2digits-6.0.1.dist-info/top_level.txt
chinese2digits-6.0.1.dist-info/RECORD
