Metadata-Version: 1.0
Name: chinese2digits
Version: 6.0.1
Summary: 最好的汉字数字(中文数字)-阿拉伯数字转换工具。包含"点二八"，"负百分之四十"等众多汉语表达方法。NLP，机器人工程必备！ The Best Tool of Chinese Number to Digits
Home-page: https://github.com/Wall-ee/chinese2digits
Author: Wa-llee
Author-email: xrli_office@foxmail.com
License: Apache License 2.0
Keywords: pip,NLP,chinese,digits_number,number_transform
Platform: all
